wechat/__init__.py
wechat/auth.py
wechat/base.py
wechat/mp.py
wechat/msg.py
wechat/pay.py
python_wechat-2021.4.29.dist-info/METADATA
python_wechat-2021.4.29.dist-info/WHEEL
python_wechat-2021.4.29.dist-info/top_level.txt
python_wechat-2021.4.29.dist-info/RECORD
