Metadata-Version: 2.1
Name: python-wechat
Version: 2021.4.29
Summary: Wechat for Python
Home-page: https://github.com/catroll/python-wechat
Author: zwczou
Author-email: zwczou@gmail.com
Maintainer: catroll
Maintainer-email: ninedoors@126.com
License: BSD
Keywords: wechat,wechat pay,wechat login,wechat mp,wechat python
Platform: any
Classifier: License :: OSI Approved :: BSD License
Classifier: Programming Language :: Python :: 3
Classifier: Programming Language :: Python :: 3.6
Classifier: Programming Language :: Python :: 3.7
Classifier: Programming Language :: Python :: 3.8
Classifier: Programming Language :: Python :: 3.9
Classifier: Programming Language :: Python :: Implementation :: CPython
Classifier: Programming Language :: Python :: Implementation :: PyPy
Requires-Dist: lxml
Requires-Dist: requests
